splent_framework/_init__.py
splent_framework/core/__init__.py
splent_framework/core/blueprints/__init__.py
splent_framework/core/blueprints/base_blueprint.py
splent_framework/core/bootstraps/__init__.py
splent_framework/core/bootstraps/locustfile_bootstrap.py
splent_framework/core/configuration/__init__.py
splent_framework/core/configuration/configuration.py
splent_framework/core/decorators/__init__.py
splent_framework/core/decorators/decorators.py
splent_framework/core/environment/__init__.py
splent_framework/core/environment/host.py
splent_framework/core/helpers/__init__.py
splent_framework/core/helpers/test_helpers_auth.py
splent_framework/core/helpers/test_helpers_db.py
splent_framework/core/locust/__init__.py
splent_framework/core/locust/common.py
splent_framework/core/managers/__init__.py
splent_framework/core/managers/config_manager.py
splent_framework/core/managers/error_handler_manager.py
splent_framework/core/managers/feature_manager.py
splent_framework/core/managers/logging_manager.py
splent_framework/core/managers/task_queue_manager.py
splent_framework/core/repositories/BaseRepository.py
splent_framework/core/repositories/__init__.py
splent_framework/core/resources/__init__.py
splent_framework/core/resources/generic_resource.py
splent_framework/core/seeders/BaseSeeder.py
splent_framework/core/seeders/__init__.py
splent_framework/core/selenium/__init__.py
splent_framework/core/selenium/common.py
splent_framework/core/serialisers/__init__.py
splent_framework/core/serialisers/serializer.py
splent_framework/core/services/BaseService.py
splent_framework/core/services/__init__.py
splent_framework-0.0.3.dist-info/licenses/LICENSE
splent_framework-0.0.3.dist-info/METADATA
splent_framework-0.0.3.dist-info/WHEEL
splent_framework-0.0.3.dist-info/top_level.txt
splent_framework-0.0.3.dist-info/RECORD
