Metadata-Version: 2.4
Name: splent_framework
Version: 0.0.3
Summary: SPLENT-FRAMEWORK is a set of libraries for agile product development within SPLENT.
Author-email: DiversoLab <diversolab@us.es>
Project-URL: Homepage, https://github.com/diverso-lab/splent_framework
Project-URL: Issues, https://github.com/diverso-lab/splent_framework/issues
Requires-Python: >=3.12
License-File: LICENSE
Requires-Dist: python-dotenv==1.0.1
Requires-Dist: sqlalchemy==2.0.37
Requires-Dist: flask==3.1.0
Requires-Dist: flask_sqlalchemy==3.1.1
Requires-Dist: flask_migrate==4.1.0
Requires-Dist: flask_session==0.8.0
Requires-Dist: flask_mail==0.10.0
Requires-Dist: flask_login==0.6.3
Requires-Dist: flask_wtf==1.2.2
Requires-Dist: redis==5.2.1
Requires-Dist: pymysql==1.1.1
Requires-Dist: psutil==6.1.1
Requires-Dist: pytz==2024.2
Dynamic: license-file
